sphinxcontrib/mdxbuilder/__init__.py
sphinxcontrib/mdxbuilder/builders/__init__.py
sphinxcontrib/mdxbuilder/builders/mdx.py
sphinxcontrib/mdxbuilder/writers/__init__.py
sphinxcontrib/mdxbuilder/writers/mdx.py
sphinxcontrib_mdxbuilder-0.1.3.dist-info/entry_points.txt
sphinxcontrib_mdxbuilder-0.1.3.dist-info/LICENSE
sphinxcontrib_mdxbuilder-0.1.3.dist-info/WHEEL
sphinxcontrib_mdxbuilder-0.1.3.dist-info/METADATA
sphinxcontrib_mdxbuilder-0.1.3.dist-info/RECORD
