Metadata-Version: 2.1
Name: sphinxcontrib-mdxbuilder
Version: 0.1.3
Summary: Sphinx extension to build MDX files
Author-email: Pedram Navid <pedram@dagsterlabs.com>
Requires-Python: >=3.10
Classifier: Development Status :: 3 - Alpha
Classifier: Environment :: Console
Classifier: Intended Audience :: Developers
Classifier: Programming Language :: Python :: 3
Classifier: Programming Language :: Python :: 3.10
Classifier: Programming Language :: Python :: 3.11
Classifier: Programming Language :: Python :: 3.12
Classifier: Framework :: Sphinx
Classifier: Framework :: Sphinx :: Extension
Requires-Dist: sphinx>=7.0
Requires-Dist: pytest ; extra == "test"
Requires-Dist: tox ; extra == "test"
Requires-Dist: tox-uv ; extra == "test"
Requires-Dist: ruff ; extra == "test"
Provides-Extra: test
